fluent_llm/__init__.py
fluent_llm/__main__.py
fluent_llm/builder.py
fluent_llm/exceptions.py
fluent_llm/messages.py
fluent_llm/model_selector.py
fluent_llm/prompt.py
fluent_llm/usage_tracker.py
fluent_llm/utils.py
fluent_llm/providers/__init__.py
fluent_llm/providers/provider.py
fluent_llm/providers/anthropic/__init__.py
fluent_llm/providers/anthropic/claude.py
fluent_llm/providers/openai/__init__.py
fluent_llm/providers/openai/gpt.py
fluent_llm-1.1.0.dist-info/licenses/LICENSE
fluent_llm-1.1.0.dist-info/METADATA
fluent_llm-1.1.0.dist-info/WHEEL
fluent_llm-1.1.0.dist-info/entry_points.txt
fluent_llm-1.1.0.dist-info/top_level.txt
fluent_llm-1.1.0.dist-info/RECORD
