Metadata-Version: 2.4
Name: fluent-llm
Version: 1.1.0
Summary: A fluent interface for working with LLMs, providing a clean and intuitive API for AI-powered applications.
Author-email: Henrik Heimbuerger <henrik@heimbuerger.de>
License-Expression: MIT
Project-URL: Homepage, https://github.com/hheimbuerger/fluent-llm
Project-URL: Source, https://github.com/hheimbuerger/fluent-llm
Requires-Python: >=3.10
License-File: LICENSE
Requires-Dist: openai>=1.99.3
Requires-Dist: anthropic>=0.56
Requires-Dist: pydantic>=2.11
Requires-Dist: pillow>=11.2.1
Dynamic: license-file
